{
  "cbsa_code": "19100",
  "cbsa_name": "Dallas-Fort Worth-Arlington, TX",
  "mdi": 0.2964,
  "bbox": [
    -99.29,
    31.32,
    -94.62,
    34.34
  ],
  "hospitals": [
    {
      "facility_id": "450015",
      "name": "PARKLAND HEALTH & HOSPITAL SYSTEM",
      "beds": 968,
      "type": "Acute Care Hospitals",
      "ownership": "Government - Hospital District or Authority",
      "lat": 32.8122,
      "lon": -96.8375,
      "govt_payer_share": 0.544,
      "medicare_discharges": 2063
    },
    {
      "facility_id": "450647",
      "name": "MEDICAL CITY DALLAS HOSPITAL",
      "beds": 963,
      "type": "Acute Care Hospitals",
      "ownership": "Proprietary",
      "lat": 32.9095,
      "lon": -96.7713,
      "govt_payer_share": 0.158,
      "medicare_discharges": 4607
    },
    {
      "facility_id": "450021",
      "name": "BAYLOR UNIVERSITY MEDICAL CENTER",
      "beds": 914,
      "type": "Acute Care Hospitals",
      "ownership": "Voluntary non-profit - Church",
      "lat": 32.7907,
      "lon": -96.7806,
      "govt_payer_share": 0.192,
      "medicare_discharges": 6843
    },
    {
      "facility_id": "450462",
      "name": "TEXAS HEALTH PRESBYTERIAN HOSPITAL DALLAS",
      "beds": 866,
      "type": "Acute Care Hospitals",
      "ownership": "Voluntary non-profit - Private",
      "lat": 32.8832,
      "lon": -96.762,
      "govt_payer_share": 0.248,
      "medicare_discharges": 5744
    },
    {
      "facility_id": "450044",
      "name": "UT OF TEXAS  SOUTHWESTERN UNIVERSITY HOSPITAL - WILLIAM P. CLEMENTS JR.",
      "beds": 826,
      "type": "Acute Care Hospitals",
      "ownership": "Government - State",
      "lat": 32.8201,
      "lon": -96.8477,
      "govt_payer_share": 0.239,
      "medicare_discharges": 7856
    },
    {
      "facility_id": "450779",
      "name": "TEXAS HEALTH HARRIS METHODIST HOSPITAL SOUTHWEST F",
      "beds": 630,
      "type": "Acute Care Hospitals",
      "ownership": "Voluntary non-profit - Private",
      "lat": 32.6577,
      "lon": -97.4193,
      "govt_payer_share": 0.241,
      "medicare_discharges": 2781
    },
    {
      "facility_id": "450651",
      "name": "MEDICAL CITY PLANO",
      "beds": 611,
      "type": "Acute Care Hospitals",
      "ownership": "Proprietary",
      "lat": 33.0193,
      "lon": -96.7664,
      "govt_payer_share": 0.208,
      "medicare_discharges": 5800
    },
    {
      "facility_id": "450135",
      "name": "TEXAS HEALTH HARRIS METHODIST FORT WORTH",
      "beds": 610,
      "type": "Acute Care Hospitals",
      "ownership": "Voluntary non-profit - Private",
      "lat": 32.7384,
      "lon": -97.3394,
      "govt_payer_share": 0.21,
      "medicare_discharges": 7891
    },
    {
      "facility_id": "450137",
      "name": "BAYLOR SCOTT AND WHITE ALL SAINTS MEDICAL CENTER",
      "beds": 538,
      "type": "Acute Care Hospitals",
      "ownership": "Voluntary non-profit - Private",
      "lat": 32.7283,
      "lon": -97.3438,
      "govt_payer_share": 0.201,
      "medicare_discharges": 3900
    },
    {
      "facility_id": "450051",
      "name": "METHODIST DALLAS MEDICAL CENTER",
      "beds": 478,
      "type": "Acute Care Hospitals",
      "ownership": "Voluntary non-profit - Other",
      "lat": 32.7608,
      "lon": -96.823,
      "govt_payer_share": 0.168,
      "medicare_discharges": 2116
    },
    {
      "facility_id": "450039",
      "name": "JPS HEALTH NETWORK",
      "beds": 429,
      "type": "Acute Care Hospitals",
      "ownership": "Government - Hospital District or Authority",
      "lat": 32.7279,
      "lon": -97.3263,
      "govt_payer_share": 0.222,
      "medicare_discharges": 1702
    },
    {
      "facility_id": "450675",
      "name": "MEDICAL CITY ARLINGTON",
      "beds": 420,
      "type": "Acute Care Hospitals",
      "ownership": "Proprietary",
      "lat": 32.6929,
      "lon": -97.1149,
      "govt_payer_share": 0.161,
      "medicare_discharges": 2406
    },
    {
      "facility_id": "450064",
      "name": "TEXAS HEALTH ARLINGTON MEMORIAL HOSPITAL",
      "beds": 369,
      "type": "Acute Care Hospitals",
      "ownership": "Voluntary non-profit - Private",
      "lat": 32.75,
      "lon": -97.1156,
      "govt_payer_share": 0.224,
      "medicare_discharges": 2024
    },
    {
      "facility_id": "450672",
      "name": "MEDICAL CITY FORT WORTH",
      "beds": 320,
      "type": "Acute Care Hospitals",
      "ownership": "Proprietary",
      "lat": 32.7284,
      "lon": -97.3179,
      "govt_payer_share": 0.246,
      "medicare_discharges": 2929
    },
    {
      "facility_id": "450079",
      "name": "BAYLOR SCOTT & WHITE MEDICAL CENTER AT IRVING",
      "beds": 288,
      "type": "Acute Care Hospitals",
      "ownership": "Voluntary non-profit - Private",
      "lat": 32.8338,
      "lon": -96.9592,
      "govt_payer_share": 0.196,
      "medicare_discharges": 2045
    },
    {
      "facility_id": "450639",
      "name": "TEXAS HEALTH HARRIS METHODIST HURST-EULESS-BEDFORD",
      "beds": 286,
      "type": "Acute Care Hospitals",
      "ownership": "Voluntary non-profit - Private",
      "lat": 32.8347,
      "lon": -97.1252,
      "govt_payer_share": 0.223,
      "medicare_discharges": 2399
    },
    {
      "facility_id": "450723",
      "name": "METHODIST CHARLTON MEDICAL CENTER",
      "beds": 285,
      "type": "Acute Care Hospitals",
      "ownership": "Voluntary non-profit - Private",
      "lat": 32.6474,
      "lon": -96.8759,
      "govt_payer_share": 0.189,
      "medicare_discharges": 2153
    },
    {
      "facility_id": "450563",
      "name": "BAYLOR SCOTT & WHITE MEDICAL CENTER  GRAPEVINE",
      "beds": 273,
      "type": "Acute Care Hospitals",
      "ownership": "Voluntary non-profit - Private",
      "lat": 32.9357,
      "lon": -97.0934,
      "govt_payer_share": 0.29,
      "medicare_discharges": 4166
    },
    {
      "facility_id": "450743",
      "name": "TEXAS HEALTH PRESBYTERIAN HOSPITAL DENTON",
      "beds": 255,
      "type": "Acute Care Hospitals",
      "ownership": "Voluntary non-profit - Private",
      "lat": 33.2172,
      "lon": -97.1671,
      "govt_payer_share": 0.277,
      "medicare_discharges": 2681
    },
    {
      "facility_id": "450678",
      "name": "WHITE ROCK MEDICAL CENTER",
      "beds": 232,
      "type": "Acute Care Hospitals",
      "ownership": "Proprietary",
      "lat": 32.8403,
      "lon": -96.704,
      "govt_payer_share": 0.242,
      "medicare_discharges": 540
    },
    {
      "facility_id": "450403",
      "name": "MEDICAL CENTER OF MCKINNEY",
      "beds": 225,
      "type": "Acute Care Hospitals",
      "ownership": "Proprietary",
      "lat": 33.1598,
      "lon": -96.6355,
      "govt_payer_share": 0.239,
      "medicare_discharges": 3004
    },
    {
      "facility_id": "450730",
      "name": "CARROLLTON REGIONAL MEDICAL CENTER",
      "beds": 216,
      "type": "Acute Care Hospitals",
      "ownership": "Proprietary",
      "lat": 33.0391,
      "lon": -96.8726,
      "govt_payer_share": 0.219,
      "medicare_discharges": 661
    },
    {
      "facility_id": "450677",
      "name": "TEXAS HEALTH HUGULEY HOSPITAL FORT WORTH SOUTH",
      "beds": 213,
      "type": "Acute Care Hospitals",
      "ownership": "Voluntary non-profit - Church",
      "lat": 32.6798,
      "lon": -97.3336,
      "govt_payer_share": 0.299,
      "medicare_discharges": 2076
    },
    {
      "facility_id": "450634",
      "name": "MEDICAL CITY DENTON",
      "beds": 208,
      "type": "Acute Care Hospitals",
      "ownership": "Proprietary",
      "lat": 33.1773,
      "lon": -97.0909,
      "govt_payer_share": 0.28,
      "medicare_discharges": 3108
    },
    {
      "facility_id": "450537",
      "name": "METHODIST RICHARDSON MEDICAL CENTER",
      "beds": 205,
      "type": "Acute Care Hospitals",
      "ownership": "Government - Hospital District or Authority",
      "lat": 32.9925,
      "lon": -96.6572,
      "govt_payer_share": 0.236,
      "medicare_discharges": 2871
    },
    {
      "facility_id": "450771",
      "name": "TEXAS HEALTH PRESBYTERIAN HOSPITAL PLANO",
      "beds": 203,
      "type": "Acute Care Hospitals",
      "ownership": "Voluntary non-profit - Private",
      "lat": 33.0451,
      "lon": -96.8358,
      "govt_payer_share": 0.234,
      "medicare_discharges": 3738
    },
    {
      "facility_id": "450669",
      "name": "MEDICAL CITY LEWISVILLE",
      "beds": 202,
      "type": "Acute Care Hospitals",
      "ownership": "Voluntary non-profit - Private",
      "lat": 33.0462,
      "lon": -97.0065,
      "govt_payer_share": 0.19,
      "medicare_discharges": 1248
    },
    {
      "facility_id": "450352",
      "name": "HUNT REGIONAL MEDICAL CENTER",
      "beds": 192,
      "type": "Acute Care Hospitals",
      "ownership": "Government - Hospital District or Authority",
      "lat": 33.1233,
      "lon": -96.1231,
      "govt_payer_share": 0.299,
      "medicare_discharges": 1907
    },
    {
      "facility_id": "450688",
      "name": "DALLAS REGIONAL MEDICAL CENTER",
      "beds": 172,
      "type": "Acute Care Hospitals",
      "ownership": "Proprietary",
      "lat": 32.7788,
      "lon": -96.6002,
      "govt_payer_share": 0.189,
      "medicare_discharges": 1091
    },
    {
      "facility_id": "450890",
      "name": "BAYLOR SCOTT & WHITE MEDICAL CENTER PLANO",
      "beds": 160,
      "type": "Acute Care Hospitals",
      "ownership": "Voluntary non-profit - Other",
      "lat": 33.0342,
      "lon": -96.8116,
      "govt_payer_share": 0.378,
      "medicare_discharges": 3282
    },
    {
      "facility_id": "450379",
      "name": "DALLAS MEDICAL CENTER",
      "beds": 155,
      "type": "Acute Care Hospitals",
      "ownership": "Proprietary",
      "lat": 32.9249,
      "lon": -96.8881,
      "govt_payer_share": 0.15,
      "medicare_discharges": 461
    },
    {
      "facility_id": "670085",
      "name": "TEXAS HEALTH HARRIS METHODIST HOSPITAL ALLIANCE",
      "beds": 151,
      "type": "Acute Care Hospitals",
      "ownership": "Voluntary non-profit - Private",
      "lat": 32.9311,
      "lon": -97.3091,
      "govt_payer_share": 0.163,
      "medicare_discharges": 1126
    },
    {
      "facility_id": "450742",
      "name": "BAYLOR SCOTT AND WHITE MEDICAL CENTER LAKE POINTE",
      "beds": 148,
      "type": "Acute Care Hospitals",
      "ownership": "Voluntary non-profit - Private",
      "lat": 32.9232,
      "lon": -96.5093,
      "govt_payer_share": 0.229,
      "medicare_discharges": 2275
    },
    {
      "facility_id": "450087",
      "name": "MEDICAL CITY NORTH HILLS",
      "beds": 140,
      "type": "Acute Care Hospitals",
      "ownership": "Proprietary",
      "lat": 32.8407,
      "lon": -97.2242,
      "govt_payer_share": 0.195,
      "medicare_discharges": 1510
    },
    {
      "facility_id": "450148",
      "name": "TEXAS HEALTH HARRIS METHODIST HOSPITAL CLEBURNE",
      "beds": 137,
      "type": "Acute Care Hospitals",
      "ownership": "Voluntary non-profit - Church",
      "lat": 32.3462,
      "lon": -97.3281,
      "govt_payer_share": 0.241,
      "medicare_discharges": 601
    },
    {
      "facility_id": "450372",
      "name": "BAYLOR SCOTT & WHITE MEDICAL CENTER- WAXAHACHIE",
      "beds": 129,
      "type": "Acute Care Hospitals",
      "ownership": "Voluntary non-profit - Private",
      "lat": 32.4257,
      "lon": -96.8474,
      "govt_payer_share": 0.265,
      "medicare_discharges": 2162
    },
    {
      "facility_id": "450885",
      "name": "BAYLOR SCOTT &  WHITE MEDICAL CENTER - CENTENNIAL",
      "beds": 118,
      "type": "Acute Care Hospitals",
      "ownership": "Voluntary non-profit - Other",
      "lat": 33.1158,
      "lon": -96.7699,
      "govt_payer_share": 0.21,
      "medicare_discharges": 1110
    },
    {
      "facility_id": "670025",
      "name": "BAYLOR SCOTT & WHITE THE HEART HOSPITAL PLANO",
      "beds": 104,
      "type": "Acute Care Hospitals",
      "ownership": "Physician",
      "lat": 33.0342,
      "lon": -96.8116,
      "govt_payer_share": 0.367,
      "medicare_discharges": 3136
    },
    {
      "facility_id": "450822",
      "name": "MEDICAL CITY LAS COLINAS",
      "beds": 100,
      "type": "Acute Care Hospitals",
      "ownership": "Proprietary",
      "lat": 32.9024,
      "lon": -96.9586,
      "govt_payer_share": 0.151,
      "medicare_discharges": 527
    },
    {
      "facility_id": "670321",
      "name": "ADVANCED DALLAS HOSPITALS AND CLINICS",
      "beds": 100,
      "type": "Acute Care Hospitals",
      "ownership": "Proprietary",
      "lat": 32.8735,
      "lon": -96.7476,
      "govt_payer_share": NaN,
      "medicare_discharges": 3
    },
    {
      "facility_id": "450203",
      "name": "MEDICAL CITY WEATHERFORD",
      "beds": 99,
      "type": "Acute Care Hospitals",
      "ownership": "Proprietary",
      "lat": 32.7476,
      "lon": -97.7861,
      "govt_payer_share": 0.325,
      "medicare_discharges": 1857
    },
    {
      "facility_id": "670068",
      "name": "TEXAS HEALTH PRESBYTERIAN HOSPITAL FLOWER MOUND",
      "beds": 99,
      "type": "Acute Care Hospitals",
      "ownership": "Proprietary",
      "lat": 33.0461,
      "lon": -97.0693,
      "govt_payer_share": 0.347,
      "medicare_discharges": 1251
    },
    {
      "facility_id": "670082",
      "name": "BAYLOR SCOTT AND WHITE  MEDICAL CENTER  MCKINNEY",
      "beds": 95,
      "type": "Acute Care Hospitals",
      "ownership": "Voluntary non-profit - Private",
      "lat": 33.2185,
      "lon": -96.6806,
      "govt_payer_share": 0.248,
      "medicare_discharges": 3114
    },
    {
      "facility_id": "450292",
      "name": "TEXAS HEALTH PRESBYTERIAN HOSPITAL KAUFMAN",
      "beds": 91,
      "type": "Acute Care Hospitals",
      "ownership": "Voluntary non-profit - Private",
      "lat": 32.5682,
      "lon": -96.2502,
      "govt_payer_share": 0.243,
      "medicare_discharges": 212
    },
    {
      "facility_id": "670023",
      "name": "METHODIST MANSFIELD MEDICAL CENTER",
      "beds": 88,
      "type": "Acute Care Hospitals",
      "ownership": "Voluntary non-profit - Private",
      "lat": 32.5693,
      "lon": -97.0951,
      "govt_payer_share": 0.202,
      "medicare_discharges": 2386
    },
    {
      "facility_id": "450271",
      "name": "MEDICAL CITY DECATUR",
      "beds": 85,
      "type": "Acute Care Hospitals",
      "ownership": "Government - Hospital District or Authority",
      "lat": 33.2763,
      "lon": -97.5142,
      "govt_payer_share": 0.3,
      "medicare_discharges": 1308
    },
    {
      "facility_id": "670090",
      "name": "CRESCENT MEDICAL CENTER LANCASTER",
      "beds": 84,
      "type": "Acute Care Hospitals",
      "ownership": "Physician",
      "lat": 32.5663,
      "lon": -96.7486,
      "govt_payer_share": 0.145,
      "medicare_discharges": 147
    },
    {
      "facility_id": "670060",
      "name": "BAYLOR SCOTT AND WHITE MEDICAL CENTER SUNNYVALE",
      "beds": 70,
      "type": "Acute Care Hospitals",
      "ownership": "Proprietary",
      "lat": 32.8005,
      "lon": -96.5476,
      "govt_payer_share": 0.239,
      "medicare_discharges": 885
    },
    {
      "facility_id": "670260",
      "name": "TEXAS HEALTH HOSPITAL FRISCO",
      "beds": 63,
      "type": "Acute Care Hospitals",
      "ownership": "Voluntary non-profit - Private",
      "lat": 33.1749,
      "lon": -96.8391,
      "govt_payer_share": 0.202,
      "medicare_discharges": 859
    },
    {
      "facility_id": "450851",
      "name": "BAYLOR SCOTT & WHITE HEART & VASCULAR HOSPITAL - DALLAS",
      "beds": 61,
      "type": "Acute Care Hospitals",
      "ownership": "Proprietary",
      "lat": 32.7831,
      "lon": -96.7766,
      "govt_payer_share": 0.329,
      "medicare_discharges": 1100
    },
    {
      "facility_id": "670044",
      "name": "TEXAS HEALTH PRESBYTERIAN HOSPITAL ROCKWALL",
      "beds": 61,
      "type": "Acute Care Hospitals",
      "ownership": "Proprietary",
      "lat": 32.8862,
      "lon": -96.4651,
      "govt_payer_share": 0.302,
      "medicare_discharges": 950
    },
    {
      "facility_id": "450833",
      "name": "ENNIS REGIONAL MEDICAL CENTER",
      "beds": 60,
      "type": "Acute Care Hospitals",
      "ownership": "Proprietary",
      "lat": 32.3239,
      "lon": -96.5903,
      "govt_payer_share": 0.346,
      "medicare_discharges": 107
    },
    {
      "facility_id": "670265",
      "name": "LEGENT ORTHOPEDIC HOSPITAL",
      "beds": 60,
      "type": "Acute Care Hospitals",
      "ownership": "Proprietary",
      "lat": 32.942,
      "lon": -97.0799,
      "govt_payer_share": NaN,
      "medicare_discharges": 99
    },
    {
      "facility_id": "670010",
      "name": "MAYHILL HOSPITAL",
      "beds": 59,
      "type": "Acute Care Hospitals",
      "ownership": "Proprietary",
      "lat": 33.2087,
      "lon": -97.0554,
      "govt_payer_share": 0.53,
      "medicare_discharges": 0
    },
    {
      "facility_id": "670309",
      "name": "TEXAS HEALTH HOSPITAL MANSFIELD",
      "beds": 59,
      "type": "Acute Care Hospitals",
      "ownership": "Proprietary",
      "lat": 32.559,
      "lon": -97.0588,
      "govt_payer_share": 0.245,
      "medicare_discharges": 211
    },
    {
      "facility_id": "670103",
      "name": "MEDICAL CITY ALLIANCE",
      "beds": 55,
      "type": "Acute Care Hospitals",
      "ownership": "Voluntary non-profit - Private",
      "lat": 32.8963,
      "lon": -97.309,
      "govt_payer_share": 0.159,
      "medicare_discharges": 946
    },
    {
      "facility_id": "670132",
      "name": "METHODIST SOUTHLAKE MEDICAL CENTER",
      "beds": 54,
      "type": "Acute Care Hospitals",
      "ownership": "Proprietary",
      "lat": 32.9545,
      "lon": -97.1489,
      "govt_payer_share": 0.178,
      "medicare_discharges": 63
    },
    {
      "facility_id": "670340",
      "name": "METHODIST CELINA MEDICAL CENTER",
      "beds": 51,
      "type": "Acute Care Hospitals",
      "ownership": "Voluntary non-profit - Private",
      "lat": 33.3389,
      "lon": -96.753,
      "govt_payer_share": 0.53,
      "medicare_discharges": 0
    },
    {
      "facility_id": "670071",
      "name": "TEXAS HEALTH HEART & VASCULAR HOSPITAL ARLINGTON",
      "beds": 48,
      "type": "Acute Care Hospitals",
      "ownership": "Proprietary",
      "lat": 32.7551,
      "lon": -97.1392,
      "govt_payer_share": 0.251,
      "medicare_discharges": 381
    },
    {
      "facility_id": "670300",
      "name": "METHODIST MIDLOTHIAN MEDICAL CENTER",
      "beds": 46,
      "type": "Acute Care Hospitals",
      "ownership": "Voluntary non-profit - Private",
      "lat": 32.5002,
      "lon": -97.0269,
      "govt_payer_share": 0.245,
      "medicare_discharges": 391
    },
    {
      "facility_id": "450419",
      "name": "TEXAS HEALTH HARRIS METHODIST HOSPITAL AZLE",
      "beds": 36,
      "type": "Acute Care Hospitals",
      "ownership": "Voluntary non-profit - Private",
      "lat": 32.9002,
      "lon": -97.5612,
      "govt_payer_share": 0.252,
      "medicare_discharges": 348
    },
    {
      "facility_id": "450872",
      "name": "USMD HOSPITAL AT ARLINGTON L P",
      "beds": 34,
      "type": "Acute Care Hospitals",
      "ownership": "Physician",
      "lat": 32.6625,
      "lon": -97.164,
      "govt_payer_share": NaN,
      "medicare_discharges": 78
    },
    {
      "facility_id": "450880",
      "name": "BAYLOR SCOTT AND WHITE SURGICAL HOSPITAL FORTWORTH",
      "beds": 34,
      "type": "Acute Care Hospitals",
      "ownership": "Physician",
      "lat": 32.7078,
      "lon": -97.3383,
      "govt_payer_share": NaN,
      "medicare_discharges": 390
    },
    {
      "facility_id": "670073",
      "name": "METHODIST HOSPITAL FOR SURGERY",
      "beds": 32,
      "type": "Acute Care Hospitals",
      "ownership": "Proprietary",
      "lat": 32.96,
      "lon": -96.8372,
      "govt_payer_share": NaN,
      "medicare_discharges": 214
    },
    {
      "facility_id": "450840",
      "name": "TEXAS HEALTH PRESBYTERIAN HOSPITAL ALLEN",
      "beds": 29,
      "type": "Acute Care Hospitals",
      "ownership": "Voluntary non-profit - Private",
      "lat": 33.1134,
      "lon": -96.6726,
      "govt_payer_share": 0.274,
      "medicare_discharges": 851
    },
    {
      "facility_id": "450422",
      "name": "BAYLOR SCOTT AND WHITE MEDICAL CENTER UPTOWN",
      "beds": 28,
      "type": "Acute Care Hospitals",
      "ownership": "Proprietary",
      "lat": 32.8022,
      "lon": -96.7889,
      "govt_payer_share": NaN,
      "medicare_discharges": 97
    },
    {
      "facility_id": "450853",
      "name": "BAYLOR SCOTT & WHITE MEDICAL CENTER - FRISCO",
      "beds": 25,
      "type": "Acute Care Hospitals",
      "ownership": "Proprietary",
      "lat": 33.1066,
      "lon": -96.8384,
      "govt_payer_share": 0.034,
      "medicare_discharges": 188
    },
    {
      "facility_id": "670067",
      "name": "BAYLOR SCOTT AND WHITE ORTHOPEDIC AND SPINE HOSPI",
      "beds": 24,
      "type": "Acute Care Hospitals",
      "ownership": "Proprietary",
      "lat": 32.6916,
      "lon": -97.136,
      "govt_payer_share": NaN,
      "medicare_discharges": 682
    },
    {
      "facility_id": "670069",
      "name": "METHODIST MCKINNEY HOSPITAL",
      "beds": 23,
      "type": "Acute Care Hospitals",
      "ownership": "Proprietary",
      "lat": 33.1547,
      "lon": -96.6967,
      "govt_payer_share": NaN,
      "medicare_discharges": 146
    },
    {
      "facility_id": "670121",
      "name": "SAINT CAMILLUS MEDICAL CENTER",
      "beds": 23,
      "type": "Acute Care Hospitals",
      "ownership": "Proprietary",
      "lat": 32.8573,
      "lon": -97.1786,
      "govt_payer_share": 0.53,
      "medicare_discharges": 0
    },
    {
      "facility_id": "450874",
      "name": "BAYLOR SURGICAL HOSPITAL AT LAS COLINAS",
      "beds": 20,
      "type": "Acute Care Hospitals",
      "ownership": "Proprietary",
      "lat": 32.9106,
      "lon": -97.0005,
      "govt_payer_share": NaN,
      "medicare_discharges": 116
    },
    {
      "facility_id": "450883",
      "name": "BAYLOR MEDICAL CENTER AT TROPHY CLUB",
      "beds": 20,
      "type": "Acute Care Hospitals",
      "ownership": "Proprietary",
      "lat": 33.0097,
      "lon": -97.22,
      "govt_payer_share": NaN,
      "medicare_discharges": 104
    },
    {
      "facility_id": "450891",
      "name": "TEXAS HEALTH CENTER FOR DIAGNOSTICS & SURGERY",
      "beds": 18,
      "type": "Acute Care Hospitals",
      "ownership": "Proprietary",
      "lat": 33.0342,
      "lon": -96.8116,
      "govt_payer_share": NaN,
      "medicare_discharges": 63
    },
    {
      "facility_id": "450888",
      "name": "TEXAS HEALTH HARRIS METHODIST HOSPITAL SOUTHLAKE",
      "beds": 17,
      "type": "Acute Care Hospitals",
      "ownership": "Proprietary",
      "lat": 32.9545,
      "lon": -97.1489,
      "govt_payer_share": NaN,
      "medicare_discharges": 74
    },
    {
      "facility_id": "670049",
      "name": "NORTH CENTRAL SURGICAL CENTER LLP",
      "beds": 17,
      "type": "Acute Care Hospitals",
      "ownership": "Voluntary non-profit - Other",
      "lat": 32.8735,
      "lon": -96.7476,
      "govt_payer_share": NaN,
      "medicare_discharges": 403
    },
    {
      "facility_id": "450893",
      "name": "THE HEART HOSPITAL BAYLOR DENTON",
      "beds": 16,
      "type": "Acute Care Hospitals",
      "ownership": "Physician",
      "lat": 33.2087,
      "lon": -97.0554,
      "govt_payer_share": 0.43,
      "medicare_discharges": 577
    },
    {
      "facility_id": "670107",
      "name": "BAYLOR SCOTT AND WHITE EMERGENCY HOSPITAL",
      "beds": 16,
      "type": "Acute Care Hospitals",
      "ownership": "Proprietary",
      "lat": 32.5327,
      "lon": -97.3065,
      "govt_payer_share": NaN,
      "medicare_discharges": 32
    },
    {
      "facility_id": "450889",
      "name": "TEXAS INSTITUTE FOR SURGERY AT PRESBYTERIAN HOSPIT",
      "beds": 9,
      "type": "Acute Care Hospitals",
      "ownership": "Physician",
      "lat": 32.8735,
      "lon": -96.7476,
      "govt_payer_share": NaN,
      "medicare_discharges": 162
    },
    {
      "facility_id": "670322",
      "name": "LEGENT SURGICAL HOSPITAL PLANO",
      "beds": 7,
      "type": "Acute Care Hospitals",
      "ownership": "Proprietary",
      "lat": 33.0213,
      "lon": -96.7416,
      "govt_payer_share": NaN,
      "medicare_discharges": 17
    },
    {
      "facility_id": "670062",
      "name": "BAYLOR EMERGENCY MEDICAL CENTER AT AUBREY",
      "beds": 2,
      "type": "Acute Care Hospitals",
      "ownership": "Proprietary",
      "lat": 33.2734,
      "lon": -96.9904,
      "govt_payer_share": NaN,
      "medicare_discharges": 61
    }
  ],
  "catchment_counties": [
    {
      "county_fips": "48113",
      "county_name": "Dallas",
      "state": "TX",
      "pop_total": 2604053,
      "pop_65_plus": 290461,
      "distance_to_hub_miles": 11.8
    },
    {
      "county_fips": "48439",
      "county_name": "Tarrant",
      "state": "TX",
      "pop_total": 2113854,
      "pop_65_plus": 247826,
      "distance_to_hub_miles": 20.0
    },
    {
      "county_fips": "48085",
      "county_name": "Collin",
      "state": "TX",
      "pop_total": 1079153,
      "pop_65_plus": 121023,
      "distance_to_hub_miles": 32.5
    },
    {
      "county_fips": "48121",
      "county_name": "Denton",
      "state": "TX",
      "pop_total": 914870,
      "pop_65_plus": 99654,
      "distance_to_hub_miles": 26.5
    },
    {
      "county_fips": "48139",
      "county_name": "Ellis",
      "state": "TX",
      "pop_total": 195509,
      "pop_65_plus": 25194,
      "distance_to_hub_miles": 35.6
    },
    {
      "county_fips": "48251",
      "county_name": "Johnson",
      "state": "TX",
      "pop_total": 182690,
      "pop_65_plus": 25532,
      "distance_to_hub_miles": 40.1
    },
    {
      "county_fips": "48367",
      "county_name": "Parker",
      "state": "TX",
      "pop_total": 151188,
      "pop_65_plus": 23745,
      "distance_to_hub_miles": 49.5
    },
    {
      "county_fips": "48257",
      "county_name": "Kaufman",
      "state": "TX",
      "pop_total": 149773,
      "pop_65_plus": 16788,
      "distance_to_hub_miles": 42.5
    },
    {
      "county_fips": "48397",
      "county_name": "Rockwall",
      "state": "TX",
      "pop_total": 110631,
      "pop_65_plus": 13674,
      "distance_to_hub_miles": 32.1
    },
    {
      "county_fips": "48231",
      "county_name": "Hunt",
      "state": "TX",
      "pop_total": 101596,
      "pop_65_plus": 16142,
      "distance_to_hub_miles": 54.1
    },
    {
      "county_fips": "48497",
      "county_name": "Wise",
      "state": "TX",
      "pop_total": 70062,
      "pop_65_plus": 10666,
      "distance_to_hub_miles": 47.8
    },
    {
      "county_fips": "48217",
      "county_name": "Hill",
      "state": "TX",
      "pop_total": 36138,
      "pop_65_plus": 7403,
      "distance_to_hub_miles": 60.0
    }
  ],
  "summary": {
    "total_beds": 15657,
    "catchment_pop": 7709517,
    "catchment_pop_65_plus": 898108,
    "catchment_pct_65_plus": 0.1165,
    "max_catchment_radius_miles": 60.0,
    "avg_catchment_distance_miles": 22.7,
    "num_counties": 12,
    "hospital_employment": 105922,
    "msa_total_employment": 3964285,
    "hospital_emp_share": 0.0214,
    "avg_govt_payer_share": 0.2562
  }
}