{
  "cbsa_code": "22380",
  "cbsa_name": "Flagstaff, AZ",
  "mdi": 0.268,
  "bbox": [
    -113.14,
    34.21,
    -109.73,
    37.92
  ],
  "hospitals": [
    {
      "facility_id": "030023",
      "name": "FLAGSTAFF MEDICAL CENTER",
      "beds": 264,
      "type": "Acute Care Hospitals",
      "ownership": "Voluntary non-profit - Private",
      "lat": 35.2094,
      "lon": -111.6447,
      "govt_payer_share": 0.65,
      "medicare_discharges": null
    },
    {
      "facility_id": "030073",
      "name": "TUBA CITY REGIONAL HEALTH CARE CORPORATION",
      "beds": 103,
      "type": "Acute Care Hospitals",
      "ownership": "Voluntary non-profit - Other",
      "lat": 36.1314,
      "lon": -111.2336,
      "govt_payer_share": 0.65,
      "medicare_discharges": null
    },
    {
      "facility_id": "031304",
      "name": "PAGE HOSPITAL",
      "beds": 25,
      "type": "Critical Access Hospitals",
      "ownership": "Government - Hospital District or Authority",
      "lat": 36.9177,
      "lon": -111.4633,
      "govt_payer_share": 0.75,
      "medicare_discharges": null
    }
  ],
  "catchment_counties": [
    {
      "county_fips": "04005",
      "county_name": "Coconino",
      "state": "AZ",
      "pop_total": 144705,
      "pop_65_plus": 19453,
      "distance_to_hub_miles": 23.7
    },
    {
      "county_fips": "04017",
      "county_name": "Navajo",
      "state": "AZ",
      "pop_total": 107110,
      "pop_65_plus": 20350,
      "distance_to_hub_miles": 68.6
    }
  ],
  "summary": {
    "total_beds": 392,
    "catchment_pop": 251815,
    "catchment_pop_65_plus": 39803,
    "catchment_pct_65_plus": 0.1581,
    "max_catchment_radius_miles": 68.6,
    "avg_catchment_distance_miles": 42.8,
    "num_counties": 2,
    "hospital_employment": 0,
    "msa_total_employment": 63798,
    "hospital_emp_share": 0.0355,
    "avg_govt_payer_share": 0.6564
  }
}