{
  "cbsa_code": "42220",
  "cbsa_name": "Santa Rosa-Petaluma, CA",
  "mdi": 0.2981,
  "bbox": [
    -124.39,
    37.25,
    -120.96,
    39.62
  ],
  "hospitals": [
    {
      "facility_id": "050174",
      "name": "PROVIDENCE SANTA ROSA MEMORIAL HOSPITAL",
      "beds": 346,
      "type": "Acute Care Hospitals",
      "ownership": "Voluntary non-profit - Private",
      "lat": 38.4429,
      "lon": -122.7021,
      "govt_payer_share": 0.449,
      "medicare_discharges": 4418
    },
    {
      "facility_id": "050690",
      "name": "KAISER FOUNDATION HOSPITAL-SANTA ROSA",
      "beds": 173,
      "type": "Acute Care Hospitals",
      "ownership": "Voluntary non-profit - Other",
      "lat": 38.4715,
      "lon": -122.7264,
      "govt_payer_share": 0.184,
      "medicare_discharges": 292
    },
    {
      "facility_id": "050291",
      "name": "SUTTER SANTA ROSA REGIONAL HOSPITAL",
      "beds": 170,
      "type": "Acute Care Hospitals",
      "ownership": "Voluntary non-profit - Other",
      "lat": 38.4963,
      "lon": -122.7512,
      "govt_payer_share": 0.468,
      "medicare_discharges": 2640
    },
    {
      "facility_id": "050136",
      "name": "PETALUMA VALLEY HOSPITAL",
      "beds": 99,
      "type": "Acute Care Hospitals",
      "ownership": "Voluntary non-profit - Other",
      "lat": 38.2537,
      "lon": -122.6335,
      "govt_payer_share": 0.309,
      "medicare_discharges": 711
    },
    {
      "facility_id": "050090",
      "name": "SONOMA VALLEY HOSPITAL",
      "beds": 83,
      "type": "Acute Care Hospitals",
      "ownership": "Government - Hospital District or Authority",
      "lat": 38.2558,
      "lon": -122.4609,
      "govt_payer_share": 0.23,
      "medicare_discharges": 390
    },
    {
      "facility_id": "051321",
      "name": "HEALDSBURG HOSPITAL",
      "beds": 26,
      "type": "Critical Access Hospitals",
      "ownership": "Voluntary non-profit - Private",
      "lat": 38.623,
      "lon": -122.8891,
      "govt_payer_share": 0.68,
      "medicare_discharges": 0
    }
  ],
  "catchment_counties": [
    {
      "county_fips": "06097",
      "county_name": "Sonoma",
      "state": "CA",
      "pop_total": 488436,
      "pop_65_plus": 100577,
      "distance_to_hub_miles": 14.3
    },
    {
      "county_fips": "06041",
      "county_name": "Marin",
      "state": "CA",
      "pop_total": 260485,
      "pop_65_plus": 60391,
      "distance_to_hub_miles": 25.8
    }
  ],
  "summary": {
    "total_beds": 897,
    "catchment_pop": 748921,
    "catchment_pop_65_plus": 160968,
    "catchment_pct_65_plus": 0.2149,
    "max_catchment_radius_miles": 25.8,
    "avg_catchment_distance_miles": 18.3,
    "num_counties": 2,
    "hospital_employment": 5381,
    "msa_total_employment": 207356,
    "hospital_emp_share": 0.026,
    "avg_govt_payer_share": 0.3726
  }
}